mcp_server_for_oscal/__init__.py
mcp_server_for_oscal/__main__.py
mcp_server_for_oscal/config.py
mcp_server_for_oscal/main.py
mcp_server_for_oscal/oscal_agent.py
mcp_server_for_oscal/py.typed
mcp_server_for_oscal/oscal_docs/awesome-oscal.md
mcp_server_for_oscal/oscal_docs/hashes.json
mcp_server_for_oscal/oscal_schemas/README.md
mcp_server_for_oscal/oscal_schemas/hashes.json
mcp_server_for_oscal/oscal_schemas/oscal_assessment-plan_schema.json
mcp_server_for_oscal/oscal_schemas/oscal_assessment-plan_schema.xsd
mcp_server_for_oscal/oscal_schemas/oscal_assessment-results_schema.json
mcp_server_for_oscal/oscal_schemas/oscal_assessment-results_schema.xsd
mcp_server_for_oscal/oscal_schemas/oscal_catalog_schema.json
mcp_server_for_oscal/oscal_schemas/oscal_catalog_schema.xsd
mcp_server_for_oscal/oscal_schemas/oscal_complete_schema.json
mcp_server_for_oscal/oscal_schemas/oscal_complete_schema.xsd
mcp_server_for_oscal/oscal_schemas/oscal_component_schema.json
mcp_server_for_oscal/oscal_schemas/oscal_component_schema.xsd
mcp_server_for_oscal/oscal_schemas/oscal_mapping_schema.json
mcp_server_for_oscal/oscal_schemas/oscal_mapping_schema.xsd
mcp_server_for_oscal/oscal_schemas/oscal_poam_schema.json
mcp_server_for_oscal/oscal_schemas/oscal_poam_schema.xsd
mcp_server_for_oscal/oscal_schemas/oscal_profile_schema.json
mcp_server_for_oscal/oscal_schemas/oscal_profile_schema.xsd
mcp_server_for_oscal/oscal_schemas/oscal_ssp_schema.json
mcp_server_for_oscal/oscal_schemas/oscal_ssp_schema.xsd
mcp_server_for_oscal/tools/README.md
mcp_server_for_oscal/tools/__init__.py
mcp_server_for_oscal/tools/get_schema.py
mcp_server_for_oscal/tools/list_models.py
mcp_server_for_oscal/tools/list_oscal_resources.py
mcp_server_for_oscal/tools/query_documentation.py
mcp_server_for_oscal/tools/utils.py
mcp_server_for_oscal-0.1.9.dist-info/METADATA
mcp_server_for_oscal-0.1.9.dist-info/WHEEL
mcp_server_for_oscal-0.1.9.dist-info/entry_points.txt
mcp_server_for_oscal-0.1.9.dist-info/licenses/LICENSE
mcp_server_for_oscal-0.1.9.dist-info/RECORD
