Metadata-Version: 2.4
Name: mcp-server-for-oscal
Version: 0.1.9
Summary: AI agent tools for Open Security Controls Assessment Language (OSCAL).
Project-URL: GitHub, https://github.com/awslabs/mcp-server-for-oscal/
Project-URL: PyPI, https://pypi.org/project/mcp-server-for-oscal/
License-Expression: Apache-2.0
License-File: LICENSE
Keywords: OSCAL,compliance-as-code,compliance-automation,continuous-compliance,mcp-server,security-as-code,security-assurance,strands-agents
Classifier: Programming Language :: Python :: 3
Classifier: Programming Language :: Python :: 3.11
Classifier: Programming Language :: Python :: 3.12
Requires-Python: >=3.11
Requires-Dist: boto3>=1.42.7
Requires-Dist: mcp>=1.23.3
Requires-Dist: strands-agents>=1.19.0
